rasa_plus/__init__.py
rasa_plus/__main__.py
rasa_plus-0.3.1.dist-info/LICENSE
rasa_plus-0.3.1.dist-info/METADATA
rasa_plus-0.3.1.dist-info/WHEEL
rasa_plus-0.3.1.dist-info/entry_points.txt
rasa_plus-0.3.1.dist-info/top_level.txt
rasa_plus-0.3.1.dist-info/RECORD
