Metadata-Version: 2.1
Name: rasa-plus
Version: 0.3.1
Summary: An organizer for your rasa bot dialogs
Home-page: https://github.com/alexandrebarbaruiva/rasa-plus
Author: Alexandre Augusto de Sá dos Santos
Author-email: alexandrebarbaruiva@gmail.com
License: UNKNOWN
Platform: UNKNOWN
Classifier: Programming Language :: Python :: 3
Classifier: License :: OSI Approved :: MIT License
Classifier: Operating System :: OS Independent
Requires-Python: >=3.6
Requires-Dist: Click
